libplf/__init__.py
libplf/piece/__init__.py
libplf/plf/__init__.py
libplf/point/__init__.py
libplf/vector/__init__.py
libplf-0.0.4.dist-info/LICENSE
libplf-0.0.4.dist-info/METADATA
libplf-0.0.4.dist-info/WHEEL
libplf-0.0.4.dist-info/top_level.txt
libplf-0.0.4.dist-info/RECORD
