Metadata-Version: 2.1
Name: libplf
Version: 0.0.4
Summary: library for multidimensional piecewise linear function
Home-page: https://github.com/libplf/libplf
Author: vang1ong7ang
Author-email: vang1ong7ang@outlook.com
License: UNKNOWN
Platform: UNKNOWN
Classifier: Programming Language :: Python :: 3
Classifier: License :: OSI Approved :: MIT License
Classifier: Operating System :: OS Independent
Requires-Python: >=3.6
